README.rst
setup.py
matrix_api_async/__init__.py
matrix_api_async/_api.py
matrix_api_async/api_asyncio.py
matrix_api_async.egg-info/PKG-INFO
matrix_api_async.egg-info/SOURCES.txt
matrix_api_async.egg-info/dependency_links.txt
matrix_api_async.egg-info/requires.txt
matrix_api_async.egg-info/top_level.txt