Metadata-Version: 1.2
Name: matrix-api-async
Version: 0.1.0
Summary: An asyncio wrapper of matrix_client.api
Home-page: https://github.com/Cadair/matrix_api_async
Author: Stuart Mumford
Author-email: stuart@cadair.com
License: MIT
Platform: UNKNOWN
Classifier: Development Status :: 2 - Pre-Alpha
Classifier: License :: OSI Approved :: MIT License
Classifier: Programming Language :: Python
Classifier: Programming Language :: Python :: 3.5
Classifier: Programming Language :: Python :: 3.6
Classifier: Programming Language :: Python :: 3.7
Requires-Python: >=3.5
